{
  "version": "6.2.0",
  "flags": {},
  "shapes": [
    {
      "label": "roof_apex",
      "points": [
        [
          450.7692307692307,
          192.26923076923075
        ]
      ],
      "group_id": null,
      "description": "",
      "shape_type": "point",
      "flags": {},
      "mask": null
    },
    {
      "label": "side_window_top_front",
      "points": [
        [
          452.30769230769226,
          204.57692307692307
        ]
      ],
      "group_id": null,
      "description": "",
      "shape_type": "point",
      "flags": {},
      "mask": null
    },
    {
      "label": "side_window_top_rear",
      "points": [
        [
          578.4615384615385,
          206.11538461538458
        ]
      ],
      "group_id": null,
      "description": "",
      "shape_type": "point",
      "flags": {},
      "mask": null
    },
    {
      "label": "front_bumper",
      "points": [
        [
          10.769230769230766,
          355.3461538461538
        ]
      ],
      "group_id": null,
      "description": "",
      "shape_type": "point",
      "flags": {},
      "mask": null
    },
    {
      "label": "rear_bumper",
      "points": [
        [
          773.8461538461538,
          333.80769230769226
        ]
      ],
      "group_id": null,
      "description": "",
      "shape_type": "point",
      "flags": {},
      "mask": null
    },
    {
      "label": "front_wheel_center",
      "points": [
        [
          150.76923076923077,
          404.57692307692304
        ]
      ],
      "group_id": null,
      "description": "",
      "shape_type": "point",
      "flags": {},
      "mask": null
    },
    {
      "label": "front_wheel_ground",
      "points": [
        [
          149.23076923076923,
          464.57692307692304
        ]
      ],
      "group_id": null,
      "description": "",
      "shape_type": "point",
      "flags": {},
      "mask": null
    },
    {
      "label": "rear_wheel_center",
      "points": [
        [
          660.0,
          403.0384615384615
        ]
      ],
      "group_id": null,
      "description": "",
      "shape_type": "point",
      "flags": {},
      "mask": null
    },
    {
      "label": "rear_wheel_ground",
      "points": [
        [
          663.0769230769231,
          461.49999999999994
        ]
      ],
      "group_id": null,
      "description": "",
      "shape_type": "point",
      "flags": {},
      "mask": null
    },
    {
      "label": "fender_arch_front",
      "points": [
        [
          153.84615384615384,
          327.65384615384613
        ]
      ],
      "group_id": null,
      "description": "",
      "shape_type": "point",
      "flags": {},
      "mask": null
    },
    {
      "label": "fender_arch_rear",
      "points": [
        [
          661.5384615384615,
          326.1153846153846
        ]
      ],
      "group_id": null,
      "description": "",
      "shape_type": "point",
      "flags": {},
      "mask": null
    },
    {
      "label": "hood_edge",
      "points": [
        [
          180.0,
          278.4230769230769
        ]
      ],
      "group_id": null,
      "description": "",
      "shape_type": "point",
      "flags": {},
      "mask": null
    },
    {
      "label": "body_waist_front",
      "points": [
        [
          395.38461538461536,
          304.57692307692304
        ]
      ],
      "group_id": null,
      "description": "",
      "shape_type": "point",
      "flags": {},
      "mask": null
    },
    {
      "label": "body_waist_rear",
      "points": [
        [
          576.9230769230769,
          289.1923076923077
        ]
      ],
      "group_id": null,
      "description": "",
      "shape_type": "point",
      "flags": {},
      "mask": null
    },
    {
      "label": "panel_front",
      "points": [
        [
          75.38461538461537,
          413.80769230769226
        ]
      ],
      "group_id": null,
      "description": "",
      "shape_type": "point",
      "flags": {},
      "mask": null
    },
    {
      "label": "panel_rear",
      "points": [
        [
          730.7692307692307,
          398.4230769230769
        ]
      ],
      "group_id": null,
      "description": "",
      "shape_type": "point",
      "flags": {},
      "mask": null
    },
    {
      "label": "windshield_base",
      "points": [
        [
          212.3076923076923,
          273.80769230769226
        ]
      ],
      "group_id": null,
      "description": "",
      "shape_type": "point",
      "flags": {},
      "mask": null
    },
    {
      "label": "rear_glass_base",
      "points": [
        [
          741.5384615384615,
          253.8076923076923
        ]
      ],
      "group_id": null,
      "description": "",
      "shape_type": "point",
      "flags": {},
      "mask": null
    },
    {
      "label": "ground_ref",
      "points": [
        [
          461.53846153846155,
          461.49999999999994
        ]
      ],
      "group_id": null,
      "description": "",
      "shape_type": "point",
      "flags": {},
      "mask": null
    }
  ],
  "imagePath": "000005_suv_side_profile_studio_shot.jpg",
  "imageData": null,
  "imageHeight": 603,
  "imageWidth": 800
}